{
  "$schema": "https://developer.microsoft.com/json-schemas/spfx/command-set-extension-manifest.schema.json",

  "id": "d480eea3-7c0b-4a49-a5da-e055291ae4ca",
  "alias": "DocumentJourneyCommandSet",
  "componentType": "Extension",
  "extensionType": "ListViewCommandSet",

  "version": "*",
  "manifestVersion": 2,

  "requiresCustomScript": false,

  "items": {
    "START_JOURNEY": {
      "title": { "default": "Start Journey" },
      "iconImageUrl": "./assets/journey-icon.svg",
      "type": "command"
    },
    "VIEW_JOURNEY": {
      "title": { "default": "View Journey" },
      "iconImageUrl": "./assets/journey-icon.svg",
      "type": "command"
    }
  }
}
